tests/test_1024.py
tests/test_ncls.py
tests/valgrind-python.supp
ncls/__init__.py
ncls/src/ncls.c
ncls/src/cncls.pxd
ncls/src/intervaldb.c
ncls/src/fintervaldb.c
ncls/src/default.h
ncls/src/ncls.pyx
ncls/src/ncls.cpython-312-x86_64-linux-musl.so
ncls/src/cncls32.pxd
ncls/src/fncls.c
ncls/src/fncls.pyx
ncls/src/ncls32.c
ncls/src/intervaldb32.h
ncls/src/ncls32.pyx
ncls/src/cgraph.h
ncls/src/ncls32.cpython-312-x86_64-linux-musl.so
ncls/src/fncls.cpython-312-x86_64-linux-musl.so
ncls/src/__init__.py
ncls/src/utarray.h
ncls/src/cfncls.pxd
ncls/src/intervaldb.h
ncls/src/fintervaldb.h
ncls/src/intervaldb32.c
examples/test_all_overlaps_both.py
examples/test_mini.csv
examples/test_fncls.py
examples/test_find_overlap_list.py
ncls-0.0.70.dist-info/WHEEL
ncls-0.0.70.dist-info/top_level.txt
ncls-0.0.70.dist-info/RECORD
ncls-0.0.70.dist-info/METADATA
ncls-0.0.70.dist-info/licenses/LICENSE
