Metadata-Version: 2.4
Name: ncls
Version: 0.0.70
Summary: A fast interval tree-like implementation in C, wrapped for the Python ecosystem.
Author-email: Endre Bakken Stovner <endbak@pm.me>
License: MIT
Project-URL: Homepage, http://github.com/pyranges/ncls
Keywords: ncls,interval-tree,genomics
Classifier: Programming Language :: Python :: 3
Classifier: Development Status :: 4 - Beta
Classifier: Environment :: Other Environment
Classifier: Intended Audience :: Developers
Classifier: Intended Audience :: Science/Research
Classifier: License :: OSI Approved :: MIT License
Classifier: Operating System :: POSIX :: Linux
Classifier: Operating System :: MacOS :: MacOS X
Classifier: Topic :: Scientific/Engineering
License-File: LICENSE
Requires-Dist: numpy
Provides-Extra: dev
Requires-Dist: black; extra == "dev"
Requires-Dist: bumpver; extra == "dev"
Requires-Dist: isort; extra == "dev"
Requires-Dist: pip-tools; extra == "dev"
Requires-Dist: pytest; extra == "dev"
Dynamic: license-file
